springdata_sqlalchemy/__init__.py
springdata_sqlalchemy/asyncio/__init__.py
springdata_sqlalchemy/asyncio/repository.py
springdata_sqlalchemy/repository.py
springdata_sqlalchemy/utils.py
spring_data_sqlachemy-0.1.3.dist-info/LICENSE
spring_data_sqlachemy-0.1.3.dist-info/WHEEL
spring_data_sqlachemy-0.1.3.dist-info/METADATA
spring_data_sqlachemy-0.1.3.dist-info/RECORD
